[
  {"id":"wheat","name":"Weizen","basePrice":12,"baseProduction":100,"unit":"Sack","category":"food","weight":1,"perishable":false},
  {"id":"fish","name":"Fisch","basePrice":8,"baseProduction":80,"unit":"Stück","category":"food","weight":1,"perishable":true},
  {"id":"wood","name":"Holz","basePrice":6,"baseProduction":120,"unit":"Balken","category":"raw","weight":2,"perishable":false},
  {"id":"iron","name":"Eisen","basePrice":15,"baseProduction":60,"unit":"Barren","category":"raw","weight":3,"perishable":false},
  {"id":"cloth","name":"Tuch","basePrice":25,"baseProduction":40,"unit":"Ballon","category":"crafted","weight":1,"perishable":false},
  {"id":"wine","name":"Wein","basePrice":35,"baseProduction":30,"unit":"Fass","category":"luxury","weight":2,"perishable":false},
  {"id":"salt","name":"Salz","basePrice":10,"baseProduction":90,"unit":"Sack","category":"food","weight":1,"perishable":false},
  {"id":"pottery","name":"Keramik","basePrice":18,"baseProduction":50,"unit":"Krug","category":"crafted","weight":1,"perishable":false}
]
